resellerinterface_api_client_python/Client.py
resellerinterface_api_client_python/__init__.py
resellerinterface_api_client_python/_version.py
resellerinterface_api_client_python/Exception/InvalidRequestException.py
resellerinterface_api_client_python/Exception/__init__.py
resellerinterface_api_client_python/Response/ApiResponse.py
resellerinterface_api_client_python/Response/ApiResponseDownload.py
resellerinterface_api_client_python/Response/__init__.py
resellerinterface_api_client_python-1.0.0.dist-info/LICENSE
resellerinterface_api_client_python-1.0.0.dist-info/METADATA
resellerinterface_api_client_python-1.0.0.dist-info/WHEEL
resellerinterface_api_client_python-1.0.0.dist-info/top_level.txt
resellerinterface_api_client_python-1.0.0.dist-info/RECORD
