Metadata-Version: 2.1
Name: resellerinterface-api-client-python
Version: 1.0.0
Summary: Python API Client
Home-page: https://github.com/resellerinterface/api-client-python
Author: ResellerInterface
License: MIT
Classifier: Development Status :: 5 - Production/Stable
Classifier: Programming Language :: Python
Classifier: Programming Language :: Python :: 3
Classifier: Programming Language :: Python :: 3.7
Classifier: Programming Language :: Python :: 3.8
Classifier: Programming Language :: Python :: 3.9
Classifier: Programming Language :: Python :: 3.10
Classifier: Programming Language :: Python :: 3.11
Classifier: License :: OSI Approved :: MIT License
Classifier: Topic :: Internet :: WWW/HTTP
License-File: LICENSE
Requires-Dist: httpx >=0.26.0
